makedown.py
makedown-0.0.8.dist-info/LICENSE
makedown-0.0.8.dist-info/METADATA
makedown-0.0.8.dist-info/WHEEL
makedown-0.0.8.dist-info/entry_points.txt
makedown-0.0.8.dist-info/top_level.txt
makedown-0.0.8.dist-info/RECORD
