Metadata-Version: 2.1
Name: makedown
Version: 0.0.8
Summary: A Markdown-based Makefile alternative.
Home-page: https://github.com/tzador/makedown
Author: Tim Zadorozhny
Author-email: tzador@gmail.com
Classifier: Programming Language :: Python :: 3
Classifier: License :: OSI Approved :: MIT License
Classifier: Operating System :: POSIX
Requires-Python: >=3
License-File: LICENSE
